{
 "title": "Proportion of Trials vs Type of Swap",
 "xlabel": "Type of Swap",
 "ylabel": "Percent of trials with one or more swaps",
 "plot_type": "bar",
 "ylim": [
  0,
  100
 ],
 "data": {
  "Our Model": {
   "x": [
    1.5,
    2.5,
    3.5,
    4.5
   ],
   "height": [
    47.0,
    8.0,
    9.0,
    0.0
   ],
   "tick_label": [
    "TT Swaps",
    "TN Swaps",
    "Both",
    "None"
   ],
   "yerr": [
    5.016135580465917,
    2.7265992434429074,
    2.8762349126466145,
    0.0
   ],
   "width": 0.5
  }
 }
}